[
    {
        "%vlocity_namespace%__DomainObjectAPIName__c": "JSON",
        "%vlocity_namespace%__DomainObjectCreationOrder__c": 0,
        "%vlocity_namespace%__DomainObjectFieldAPIName__c": "%vlocity_namespace%__CpqConfigurationSetup__c",
        "%vlocity_namespace%__FilterGroup__c": 1,
        "%vlocity_namespace%__FilterOperator__c": "=",
        "%vlocity_namespace%__FilterValue__c": "Id",
        "%vlocity_namespace%__InterfaceFieldAPIName__c": "Id",
        "%vlocity_namespace%__InterfaceObjectLookupOrder__c": 1,
        "%vlocity_namespace%__InterfaceObjectName__c": "%vlocity_namespace%__CpqConfigurationSetup__c",
        "%vlocity_namespace%__MapId__c": "CPQ Configuration Setup Migration0",
        "Name": "CPQ Configuration Setup Migration",
        "VlocityDataPackType": "SObject",
        "VlocityRecordSObjectType": "%vlocity_namespace%__DRMapItem__c"
    },
    {
        "%vlocity_namespace%__ConfigurationAttribute__c": "Global",
        "%vlocity_namespace%__ConfigurationCategory__c": "Ignore Field",
        "%vlocity_namespace%__ConfigurationProcess__c": "All",
        "%vlocity_namespace%__ConfigurationType__c": "Action",
        "%vlocity_namespace%__ConfigurationValue__c": "%vlocity_namespace%__DRBundleName__c",
        "%vlocity_namespace%__DomainObjectAPIName__c": "JSON",
        "%vlocity_namespace%__DomainObjectCreationOrder__c": 0,
        "%vlocity_namespace%__DomainObjectFieldAPIName__c": "Configuration",
        "%vlocity_namespace%__MapId__c": "CPQ Configuration Setup Migration11",
        "Name": "CPQ Configuration Setup Migration",
        "VlocityDataPackType": "SObject",
        "VlocityRecordSObjectType": "%vlocity_namespace%__DRMapItem__c"
    },
    {
        "%vlocity_namespace%__ConfigurationAttribute__c": "Global",
        "%vlocity_namespace%__ConfigurationCategory__c": "Ignore Field",
        "%vlocity_namespace%__ConfigurationProcess__c": "All",
        "%vlocity_namespace%__ConfigurationType__c": "Action",
        "%vlocity_namespace%__ConfigurationValue__c": "%vlocity_namespace%__DRError__c",
        "%vlocity_namespace%__DomainObjectAPIName__c": "JSON",
        "%vlocity_namespace%__DomainObjectCreationOrder__c": 0,
        "%vlocity_namespace%__DomainObjectFieldAPIName__c": "Configuration",
        "%vlocity_namespace%__MapId__c": "CPQ Configuration Setup Migration13",
        "Name": "CPQ Configuration Setup Migration",
        "VlocityDataPackType": "SObject",
        "VlocityRecordSObjectType": "%vlocity_namespace%__DRMapItem__c"
    },
    {
        "%vlocity_namespace%__ConfigurationAttribute__c": "Global",
        "%vlocity_namespace%__ConfigurationCategory__c": "Ignore Field",
        "%vlocity_namespace%__ConfigurationProcess__c": "All",
        "%vlocity_namespace%__ConfigurationType__c": "Action",
        "%vlocity_namespace%__ConfigurationValue__c": "%vlocity_namespace%__DRProgressData__c",
        "%vlocity_namespace%__DomainObjectAPIName__c": "JSON",
        "%vlocity_namespace%__DomainObjectCreationOrder__c": 0,
        "%vlocity_namespace%__DomainObjectFieldAPIName__c": "Configuration",
        "%vlocity_namespace%__MapId__c": "CPQ Configuration Setup Migration12",
        "Name": "CPQ Configuration Setup Migration",
        "VlocityDataPackType": "SObject",
        "VlocityRecordSObjectType": "%vlocity_namespace%__DRMapItem__c"
    },
    {
        "%vlocity_namespace%__ConfigurationAttribute__c": "Global",
        "%vlocity_namespace%__ConfigurationCategory__c": "Ignore Field",
        "%vlocity_namespace%__ConfigurationProcess__c": "All",
        "%vlocity_namespace%__ConfigurationType__c": "Action",
        "%vlocity_namespace%__ConfigurationValue__c": "%vlocity_namespace%__DRStatus__c",
        "%vlocity_namespace%__DomainObjectAPIName__c": "JSON",
        "%vlocity_namespace%__DomainObjectCreationOrder__c": 0,
        "%vlocity_namespace%__DomainObjectFieldAPIName__c": "Configuration",
        "%vlocity_namespace%__MapId__c": "CPQ Configuration Setup Migration14",
        "Name": "CPQ Configuration Setup Migration",
        "VlocityDataPackType": "SObject",
        "VlocityRecordSObjectType": "%vlocity_namespace%__DRMapItem__c"
    },
    {
        "%vlocity_namespace%__ConfigurationAttribute__c": "Global",
        "%vlocity_namespace%__ConfigurationCategory__c": "Ignore Field",
        "%vlocity_namespace%__ConfigurationProcess__c": "All",
        "%vlocity_namespace%__ConfigurationType__c": "Action",
        "%vlocity_namespace%__ConfigurationValue__c": "CreatedById",
        "%vlocity_namespace%__DomainObjectAPIName__c": "JSON",
        "%vlocity_namespace%__DomainObjectCreationOrder__c": 0,
        "%vlocity_namespace%__DomainObjectFieldAPIName__c": "Configuration",
        "%vlocity_namespace%__MapId__c": "CPQ Configuration Setup Migration4",
        "Name": "CPQ Configuration Setup Migration",
        "VlocityDataPackType": "SObject",
        "VlocityRecordSObjectType": "%vlocity_namespace%__DRMapItem__c"
    },
    {
        "%vlocity_namespace%__ConfigurationAttribute__c": "Global",
        "%vlocity_namespace%__ConfigurationCategory__c": "Ignore Field",
        "%vlocity_namespace%__ConfigurationProcess__c": "All",
        "%vlocity_namespace%__ConfigurationType__c": "Action",
        "%vlocity_namespace%__ConfigurationValue__c": "CreatedDate",
        "%vlocity_namespace%__DomainObjectAPIName__c": "JSON",
        "%vlocity_namespace%__DomainObjectCreationOrder__c": 0,
        "%vlocity_namespace%__DomainObjectFieldAPIName__c": "Configuration",
        "%vlocity_namespace%__MapId__c": "CPQ Configuration Setup Migration3",
        "Name": "CPQ Configuration Setup Migration",
        "VlocityDataPackType": "SObject",
        "VlocityRecordSObjectType": "%vlocity_namespace%__DRMapItem__c"
    },
    {
        "%vlocity_namespace%__ConfigurationAttribute__c": "Global",
        "%vlocity_namespace%__ConfigurationCategory__c": "Ignore Field",
        "%vlocity_namespace%__ConfigurationProcess__c": "All",
        "%vlocity_namespace%__ConfigurationType__c": "Action",
        "%vlocity_namespace%__ConfigurationValue__c": "IsCustomerPortal",
        "%vlocity_namespace%__DomainObjectAPIName__c": "JSON",
        "%vlocity_namespace%__DomainObjectCreationOrder__c": 0,
        "%vlocity_namespace%__DomainObjectFieldAPIName__c": "Configuration",
        "%vlocity_namespace%__MapId__c": "CPQ Configuration Setup Migration7",
        "Name": "CPQ Configuration Setup Migration",
        "VlocityDataPackType": "SObject",
        "VlocityRecordSObjectType": "%vlocity_namespace%__DRMapItem__c"
    },
    {
        "%vlocity_namespace%__ConfigurationAttribute__c": "Global",
        "%vlocity_namespace%__ConfigurationCategory__c": "Ignore Field",
        "%vlocity_namespace%__ConfigurationProcess__c": "All",
        "%vlocity_namespace%__ConfigurationType__c": "Action",
        "%vlocity_namespace%__ConfigurationValue__c": "IsDeleted",
        "%vlocity_namespace%__DomainObjectAPIName__c": "JSON",
        "%vlocity_namespace%__DomainObjectCreationOrder__c": 0,
        "%vlocity_namespace%__DomainObjectFieldAPIName__c": "Configuration",
        "%vlocity_namespace%__MapId__c": "CPQ Configuration Setup Migration2",
        "Name": "CPQ Configuration Setup Migration",
        "VlocityDataPackType": "SObject",
        "VlocityRecordSObjectType": "%vlocity_namespace%__DRMapItem__c"
    },
    {
        "%vlocity_namespace%__ConfigurationAttribute__c": "Global",
        "%vlocity_namespace%__ConfigurationCategory__c": "Ignore Field",
        "%vlocity_namespace%__ConfigurationProcess__c": "All",
        "%vlocity_namespace%__ConfigurationType__c": "Action",
        "%vlocity_namespace%__ConfigurationValue__c": "IsPartner",
        "%vlocity_namespace%__DomainObjectAPIName__c": "JSON",
        "%vlocity_namespace%__DomainObjectCreationOrder__c": 0,
        "%vlocity_namespace%__DomainObjectFieldAPIName__c": "Configuration",
        "%vlocity_namespace%__MapId__c": "CPQ Configuration Setup Migration8",
        "Name": "CPQ Configuration Setup Migration",
        "VlocityDataPackType": "SObject",
        "VlocityRecordSObjectType": "%vlocity_namespace%__DRMapItem__c"
    },
    {
        "%vlocity_namespace%__ConfigurationAttribute__c": "Global",
        "%vlocity_namespace%__ConfigurationCategory__c": "Ignore Field",
        "%vlocity_namespace%__ConfigurationProcess__c": "All",
        "%vlocity_namespace%__ConfigurationType__c": "Action",
        "%vlocity_namespace%__ConfigurationValue__c": "LastModifiedById",
        "%vlocity_namespace%__DomainObjectAPIName__c": "JSON",
        "%vlocity_namespace%__DomainObjectCreationOrder__c": 0,
        "%vlocity_namespace%__DomainObjectFieldAPIName__c": "Configuration",
        "%vlocity_namespace%__MapId__c": "CPQ Configuration Setup Migration9",
        "Name": "CPQ Configuration Setup Migration",
        "VlocityDataPackType": "SObject",
        "VlocityRecordSObjectType": "%vlocity_namespace%__DRMapItem__c"
    },
    {
        "%vlocity_namespace%__ConfigurationAttribute__c": "Global",
        "%vlocity_namespace%__ConfigurationCategory__c": "Ignore Field",
        "%vlocity_namespace%__ConfigurationProcess__c": "All",
        "%vlocity_namespace%__ConfigurationType__c": "Action",
        "%vlocity_namespace%__ConfigurationValue__c": "LastModifiedDate",
        "%vlocity_namespace%__DomainObjectAPIName__c": "JSON",
        "%vlocity_namespace%__DomainObjectCreationOrder__c": 0,
        "%vlocity_namespace%__DomainObjectFieldAPIName__c": "Configuration",
        "%vlocity_namespace%__MapId__c": "CPQ Configuration Setup Migration5",
        "Name": "CPQ Configuration Setup Migration",
        "VlocityDataPackType": "SObject",
        "VlocityRecordSObjectType": "%vlocity_namespace%__DRMapItem__c"
    },
    {
        "%vlocity_namespace%__ConfigurationAttribute__c": "Global",
        "%vlocity_namespace%__ConfigurationCategory__c": "Ignore Field",
        "%vlocity_namespace%__ConfigurationProcess__c": "All",
        "%vlocity_namespace%__ConfigurationType__c": "Action",
        "%vlocity_namespace%__ConfigurationValue__c": "OwnerId",
        "%vlocity_namespace%__DomainObjectAPIName__c": "JSON",
        "%vlocity_namespace%__DomainObjectCreationOrder__c": 0,
        "%vlocity_namespace%__DomainObjectFieldAPIName__c": "Configuration",
        "%vlocity_namespace%__MapId__c": "CPQ Configuration Setup Migration1",
        "Name": "CPQ Configuration Setup Migration",
        "VlocityDataPackType": "SObject",
        "VlocityRecordSObjectType": "%vlocity_namespace%__DRMapItem__c"
    },
    {
        "%vlocity_namespace%__ConfigurationAttribute__c": "Global",
        "%vlocity_namespace%__ConfigurationCategory__c": "Ignore Field",
        "%vlocity_namespace%__ConfigurationProcess__c": "All",
        "%vlocity_namespace%__ConfigurationType__c": "Action",
        "%vlocity_namespace%__ConfigurationValue__c": "SetupOwnerId",
        "%vlocity_namespace%__DomainObjectAPIName__c": "JSON",
        "%vlocity_namespace%__DomainObjectCreationOrder__c": 0,
        "%vlocity_namespace%__DomainObjectFieldAPIName__c": "Configuration",
        "%vlocity_namespace%__MapId__c": "CPQ Configuration Setup Migration10",
        "Name": "CPQ Configuration Setup Migration",
        "VlocityDataPackType": "SObject",
        "VlocityRecordSObjectType": "%vlocity_namespace%__DRMapItem__c"
    },
    {
        "%vlocity_namespace%__ConfigurationAttribute__c": "Global",
        "%vlocity_namespace%__ConfigurationCategory__c": "Ignore Field",
        "%vlocity_namespace%__ConfigurationProcess__c": "All",
        "%vlocity_namespace%__ConfigurationType__c": "Action",
        "%vlocity_namespace%__ConfigurationValue__c": "SystemModstamp",
        "%vlocity_namespace%__DomainObjectAPIName__c": "JSON",
        "%vlocity_namespace%__DomainObjectCreationOrder__c": 0,
        "%vlocity_namespace%__DomainObjectFieldAPIName__c": "Configuration",
        "%vlocity_namespace%__MapId__c": "CPQ Configuration Setup Migration6",
        "Name": "CPQ Configuration Setup Migration",
        "VlocityDataPackType": "SObject",
        "VlocityRecordSObjectType": "%vlocity_namespace%__DRMapItem__c"
    }
]